[
  {
    "title": "Concord Select Board, 7/3/18",
    "path": "/vod/concordselect/2018/070318",
    "nid": 1549,
    "cablecastShowId": 6857,
    "date": "2018-07-03",
    "location": "Concord Municipal Building",
    "year": "2018",
    "yearPath": "/vod/year/2018",
    "categories": [
      {
        "name": "Public Meetings",
        "path": "/vod/public-meetings"
      },
      {
        "name": "Concord Select Board",
        "path": "/vod/concordselect"
      }
    ],
    "teaserImage": null,
    "videoSource": "archive.org",
    "videoId": "katv-concordselect-mtg-070318-6857"
  },
  {
    "title": "St. Johnsbury School Board, 7/9/18",
    "path": "/vod/stjschool/2018/070918",
    "nid": 1556,
    "cablecastShowId": 6869,
    "date": "2018-07-09",
    "location": "St. Johnsbury School",
    "year": "2018",
    "yearPath": "/vod/year/2018",
    "categories": [
      {
        "name": "Public Meetings",
        "path": "/vod/public-meetings"
      },
      {
        "name": "St. Johnsbury School Board",
        "path": "/vod/stjschool"
      }
    ],
    "teaserImage": null,
    "videoSource": "archive.org",
    "videoId": "katv-stjschool-mtg-070918-6869"
  },
  {
    "title": "St. Johnsbury Select Board, 7/23/18",
    "path": "/vod/stjselect/2018/072318",
    "nid": 1564,
    "cablecastShowId": 6903,
    "date": "2018-07-23",
    "location": "St. Johnsbury Welcome Center",
    "year": "2018",
    "yearPath": "/vod/year/2018",
    "categories": [
      {
        "name": "Public Meetings",
        "path": "/vod/public-meetings"
      },
      {
        "name": "St. Johnsbury Select Board",
        "path": "/vod/stjselect"
      }
    ],
    "teaserImage": null,
    "videoSource": "archive.org",
    "videoId": "katv-stjselect-mtg-072318-6903"
  },
  {
    "title": "St. Johnsbury Academy Theatre Presents: Antony and Cleopatra",
    "path": "/vod/concerts/2018/sjatheater072518",
    "nid": 782,
    "cablecastShowId": 6914,
    "date": "2018-07-25",
    "location": "St. Johnsbury Academy",
    "year": "2018",
    "yearPath": "/vod/year/2018",
    "categories": [
      {
        "name": "Concerts",
        "path": "/vod/concerts"
      },
      {
        "name": "St. Johnsbury Academy",
        "path": "/vod/concerts/sja"
      }
    ],
    "teaserImage": null,
    "videoSource": "vimeo",
    "videoId": "282071004"
  },
  {
    "title": "Catamount Arts: Fredrick Douglas, The Meaning of Fourth of July",
    "path": "/vod/forums/2018/catamount070218",
    "nid": 1543,
    "cablecastShowId": 6856,
    "date": "2018-07-02",
    "location": "St. Johnsbury Athenaeum",
    "year": "2018",
    "yearPath": "/vod/year/2018",
    "categories": [
      {
        "name": "Lectures and Forums",
        "path": "/vod/lectures-forums"
      },
      {
        "name": "Catamount Arts",
        "path": "/vod/catamount"
      }
    ],
    "teaserImage": null,
    "videoSource": "vimeo",
    "videoId": "279594565"
  },
  {
    "title": "St. Johnsbury Athenaeum: Readings in the Gallery, Nicole Homer Austin",
    "path": "/vod/lectures/2018/stjath070518",
    "nid": 1554,
    "cablecastShowId": 6861,
    "date": "2018-07-05",
    "location": "St. Johnsbury Athenaeum",
    "year": "2018",
    "yearPath": "/vod/year/2018",
    "categories": [
      {
        "name": "Lectures and Forums",
        "path": "/vod/lectures-forums"
      },
      {
        "name": "St. Johnsbury Athenaeum",
        "path": "/vod/stjath"
      }
    ],
    "teaserImage": null,
    "videoSource": "vimeo",
    "videoId": "279537109"
  },
  {
    "title": "Woodsville 4th of July Parade 2018",
    "path": "/vod/other/2018/woodsville4th070418",
    "nid": 1555,
    "cablecastShowId": 6859,
    "date": "2018-07-04",
    "location": "Woodsville, NH",
    "year": "2018",
    "yearPath": "/vod/year/2018",
    "categories": [
      {
        "name": "Other Programs",
        "path": "/vod/other"
      }
    ],
    "teaserImage": null,
    "videoSource": "vimeo",
    "videoId": "279000100"
  },
  {
    "title": "In & Around St. J: July 2018 Events",
    "path": "/vod/studio/2018/iastj071018",
    "nid": 1557,
    "cablecastShowId": 6873,
    "date": "2018-07-10",
    "location": "KATV Studio",
    "year": "2018",
    "yearPath": "/vod/year/2018",
    "categories": [
      {
        "name": "Studio Programs",
        "path": "/vod/studio"
      },
      {
        "name": "In & Around St. J",
        "path": "/vod/studio/iastj"
      }
    ],
    "teaserImage": null,
    "videoSource": "vimeo",
    "videoId": "280856166"
  },
  {
    "title": "Academy Theatre: Antony and Cleopatra Promo",
    "path": "/vod/studio/2018/sja071318",
    "nid": 1558,
    "cablecastShowId": 6883,
    "date": "2018-07-13",
    "location": "KATV Studio",
    "year": "2018",
    "yearPath": "/vod/year/2018",
    "categories": [
      {
        "name": "Studio Programs",
        "path": "/vod/studio"
      }
    ],
    "teaserImage": null,
    "videoSource": "vimeo",
    "videoId": "280854045"
  },
  {
    "title": "St. Johnsbury Athenaeum: Readings in the Gallery, Jessica Aiken-Hall",
    "path": "/vod/lectures/2018/stjath071818",
    "nid": 1559,
    "cablecastShowId": 6896,
    "date": "2018-07-18",
    "location": "St. Johnsbury Athenaeum",
    "year": "2018",
    "yearPath": "/vod/year/2018",
    "categories": [
      {
        "name": "Lectures and Forums",
        "path": "/vod/lectures-forums"
      },
      {
        "name": "St. Johnsbury Athenaeum",
        "path": "/vod/stjath"
      }
    ],
    "teaserImage": null,
    "videoSource": "vimeo",
    "videoId": "280855776"
  },
  {
    "title": "38th Annual Stars and Stripes Parade",
    "path": "/vod/other/2018/starsstripes072118",
    "nid": 1563,
    "cablecastShowId": 6901,
    "date": "2018-07-21",
    "location": "Lyndonville",
    "year": "2018",
    "yearPath": "/vod/year/2018",
    "categories": [
      {
        "name": "Other Programs",
        "path": "/vod/other"
      }
    ],
    "teaserImage": null,
    "videoSource": "vimeo",
    "videoId": "282069126"
  }
]