[
  {
    "title": "St. Johnsbury Select Board, 1/14/19, Special Appropriations Public Address",
    "path": "/vod/stjselect/2019/011419specmtg",
    "nid": 1637,
    "cablecastShowId": 7281,
    "date": "2019-01-14",
    "location": "St. Johnsbury Welcome Center",
    "year": "2019",
    "yearPath": "/vod/year/2019",
    "categories": [
      {
        "name": "Public Meetings",
        "path": "/vod/public-meetings"
      },
      {
        "name": "St. Johnsbury Select Board",
        "path": "/vod/stjselect"
      }
    ],
    "teaserImage": null,
    "videoSource": "archive.org",
    "videoId": "katv-stjselect-specmtg-011419-7281"
  },
  {
    "title": "St. Johnsbury Select Board, 1/14/19",
    "path": "/vod/stjselect/2019/011419",
    "nid": 1644,
    "cablecastShowId": 7278,
    "date": "2019-01-14",
    "location": "St. Johnsbury Welcome Center",
    "year": "2019",
    "yearPath": "/vod/year/2019",
    "categories": [
      {
        "name": "Public Meetings",
        "path": "/vod/public-meetings"
      },
      {
        "name": "St. Johnsbury Select Board",
        "path": "/vod/stjselect"
      }
    ],
    "teaserImage": null,
    "videoSource": "archive.org",
    "videoId": "katv-stjselect-mtg-011419-7278"
  },
  {
    "title": "St. Johnsbury School Board, 1/14/19",
    "path": "/vod/stjschool/2019/011419",
    "nid": 1645,
    "cablecastShowId": 7279,
    "date": "2019-01-14",
    "location": "St. Johnsbury School",
    "year": "2019",
    "yearPath": "/vod/year/2019",
    "categories": [
      {
        "name": "Public Meetings",
        "path": "/vod/public-meetings"
      },
      {
        "name": "St. Johnsbury School Board",
        "path": "/vod/stjschool"
      }
    ],
    "teaserImage": null,
    "videoSource": "archive.org",
    "videoId": "katv-stjschool-mtg-011419-7279"
  },
  {
    "title": "St. Johnsbury Select Board, 1/28/19",
    "path": "/vod/stjselect/2019/012819",
    "nid": 1646,
    "cablecastShowId": 7320,
    "date": "2019-01-28",
    "location": "St. Johnsbury Welcome Center",
    "year": "2019",
    "yearPath": "/vod/year/2019",
    "categories": [
      {
        "name": "Public Meetings",
        "path": "/vod/public-meetings"
      },
      {
        "name": "St. Johnsbury Select Board",
        "path": "/vod/stjselect"
      }
    ],
    "teaserImage": null,
    "videoSource": "archive.org",
    "videoId": "katv-stjselect-mtg-012819-7320"
  },
  {
    "title": "CCSU Board of Directors, 1/21/19",
    "path": "/vod/forums/2019/ccsubod012119",
    "nid": 1677,
    "cablecastShowId": 7302,
    "date": "2019-01-21",
    "location": "Barnett",
    "year": "2019",
    "yearPath": "/vod/year/2019",
    "categories": [
      {
        "name": "Public Meetings",
        "path": "/vod/public-meetings"
      },
      {
        "name": "CCSU Board of Directors",
        "path": "/vod/ccsubod"
      }
    ],
    "teaserImage": null,
    "videoSource": "archive.org",
    "videoId": "katv-ccsubod-mtg-012119-7302"
  },
  {
    "title": "Lyndon Institute: LI've 2019",
    "path": "/vod/concerts/2019/li011819",
    "nid": 763,
    "cablecastShowId": 7294,
    "date": "2019-01-18",
    "location": "Lyndon Institute",
    "year": "2019",
    "yearPath": "/vod/year/2019",
    "categories": [
      {
        "name": "Concerts",
        "path": "/vod/concerts"
      },
      {
        "name": "Lyndon Institute",
        "path": "/vod/concerts/li"
      }
    ],
    "teaserImage": null,
    "videoSource": "vimeo",
    "videoId": "314821770"
  },
  {
    "title": "What's Going On? Headlines, Measure of Society",
    "path": "/vod/wgo/wgo011719",
    "nid": 1634,
    "cablecastShowId": 7287,
    "date": "2019-01-17",
    "location": "KATV Studio",
    "year": "2019",
    "yearPath": "/vod/year/2019",
    "categories": [
      {
        "name": "Studio Programs",
        "path": "/vod/studio"
      },
      {
        "name": "What's Going On?",
        "path": "/vod/studio/wgo"
      }
    ],
    "teaserImage": null,
    "videoSource": "vimeo",
    "videoId": "314777448"
  },
  {
    "title": "FoodWorx Enterprises: What's Brewing in St. J?",
    "path": "/vod/forums/2019/brewingstj012419",
    "nid": 1638,
    "cablecastShowId": 7317,
    "date": "2019-01-24",
    "location": "St. Johnsbury Academy",
    "year": "2019",
    "yearPath": "/vod/year/2019",
    "categories": [
      {
        "name": "Lectures and Forums",
        "path": "/vod/lectures-forums"
      }
    ],
    "teaserImage": null,
    "videoSource": "vimeo",
    "videoId": "314948764"
  },
  {
    "title": "Legislative Breakfast, January 2019",
    "path": "/vod/legbkfst/2019/012819",
    "nid": 1639,
    "cablecastShowId": 7318,
    "date": "2019-01-28",
    "location": "St. Johnsbury House",
    "year": "2019",
    "yearPath": "/vod/year/2019",
    "categories": [
      {
        "name": "NEK Legislative Breakfast",
        "path": "/vod/neklegbkfst"
      },
      {
        "name": "Local Politics",
        "path": "/vod/politics"
      }
    ],
    "teaserImage": null,
    "videoSource": "vimeo",
    "videoId": "314947772"
  },
  {
    "title": "What's Going On? At a Loss for Words",
    "path": "/vod/wgo/wgo013119",
    "nid": 1752,
    "cablecastShowId": 7347,
    "date": "2019-01-31",
    "location": "KATV Studio",
    "year": "2019",
    "yearPath": "/vod/year/2019",
    "categories": [
      {
        "name": "Studio Programs",
        "path": "/vod/studio"
      },
      {
        "name": "What's Going On?",
        "path": "/vod/studio/wgo"
      }
    ],
    "teaserImage": null,
    "videoSource": "vimeo",
    "videoId": "343939903"
  }
]