[
  {
    "title": "STJ Town Band: 2024 Holiday Concert",
    "path": "/vod/concerts/2024/stjtown20241201",
    "nid": 2642,
    "cablecastShowId": 13597,
    "date": "2024-12-01",
    "location": "United Community Church",
    "year": "2024",
    "yearPath": "/vod/year/2024",
    "categories": [
      {
        "name": "Concerts",
        "path": "/vod/concerts"
      }
    ],
    "teaserImage": "/assets/images/vod/2024/stjtown20241201.jpg",
    "videoSource": "vimeo",
    "videoId": "1035988295"
  },
  {
    "title": "St. Johnsbury School Board, 12/2/24",
    "path": "/vod/stjschool/2024/20241202",
    "nid": 2643,
    "cablecastShowId": 13564,
    "date": "2024-12-02",
    "location": "St. Johnsbury",
    "year": "2024",
    "yearPath": "/vod/year/2024",
    "categories": [
      {
        "name": "Public Meetings",
        "path": "/vod/public-meetings"
      },
      {
        "name": "St. Johnsbury School Board",
        "path": "/vod/stjschool"
      }
    ],
    "teaserImage": "/assets/images/vod/2024/stjschool20241202.jpg",
    "videoSource": "archive.org",
    "videoId": "katv-stjschool-mtg-120224-13564"
  },
  {
    "title": "Concord Select Board, 12/3/24",
    "path": "/vod/concordselect/2024/20241203",
    "nid": 2644,
    "cablecastShowId": 13565,
    "date": "2024-12-03",
    "location": "Concord",
    "year": "2024",
    "yearPath": "/vod/year/2024",
    "categories": [
      {
        "name": "Public Meetings",
        "path": "/vod/public-meetings"
      },
      {
        "name": "Concord Select Board",
        "path": "/vod/concordselect"
      }
    ],
    "teaserImage": "/assets/images/vod/2024/concordselect20241203.jpg",
    "videoSource": "archive.org",
    "videoId": "katv-concordselect-mtg-120324-13565"
  },
  {
    "title": "350 VT: Third Act, Orange East",
    "path": "/vod/lectures/2024/350vt20241205",
    "nid": 2645,
    "cablecastShowId": 13574,
    "date": "2024-12-11",
    "location": "Newbury",
    "year": "2024",
    "yearPath": "/vod/year/2024",
    "categories": [
      {
        "name": "Lectures and Forums",
        "path": "/vod/lectures-forums"
      }
    ],
    "teaserImage": "/assets/images/vod/2024/350vt20241205.jpg",
    "videoSource": "vimeo",
    "videoId": "1037272914"
  },
  {
    "title": "Groton Select Board, 12/5/24",
    "path": "/vod/grotonselect/2024/20241205",
    "nid": 2646,
    "cablecastShowId": 13566,
    "date": "2024-12-05",
    "location": "Groton",
    "year": "2024",
    "yearPath": "/vod/year/2024",
    "categories": [
      {
        "name": "Public Meetings",
        "path": "/vod/public-meetings"
      },
      {
        "name": "Groton Select Board",
        "path": "/vod/grotonselect"
      }
    ],
    "teaserImage": "/assets/images/vod/2024/grotonselect20241205.jpg",
    "videoSource": "archive.org",
    "videoId": "katv-grotonselect-mtg-120524-13566"
  },
  {
    "title": "What's Going On? B.R.I.C.S. vs. Bretton Woods",
    "path": "/vod/wgo/wgo20241206",
    "nid": 2647,
    "cablecastShowId": 13621,
    "date": "2024-12-06",
    "location": "KATV Studio",
    "year": "2024",
    "yearPath": "/vod/year/2024",
    "categories": [
      {
        "name": "Studio Programs",
        "path": "/vod/studio"
      },
      {
        "name": "What's Going On?",
        "path": "/vod/studio/wgo"
      }
    ],
    "teaserImage": "/assets/images/vod/2024/wgo20241206.jpg",
    "videoSource": "vimeo",
    "videoId": "1037272631"
  },
  {
    "title": "North Country Chorus: 2024 Holiday Concert",
    "path": "/vod/concerts/2024/ncc20241208",
    "nid": 2648,
    "cablecastShowId": 13575,
    "date": "2024-12-08",
    "location": "United Community Church",
    "year": "2024",
    "yearPath": "/vod/year/2024",
    "categories": [
      {
        "name": "Concerts",
        "path": "/vod/concerts"
      }
    ],
    "teaserImage": "/assets/images/vod/2024/ncc20241208.jpg",
    "videoSource": "vimeo",
    "videoId": "1038402364"
  },
  {
    "title": "St. Johnsbury Select Board, 12/9/24",
    "path": "/vod/stjselect/2024/20241209",
    "nid": 2649,
    "cablecastShowId": 13583,
    "date": "2024-12-09",
    "location": "St. Johnsbury Welcome Center",
    "year": "2024",
    "yearPath": "/vod/year/2024",
    "categories": [
      {
        "name": "Public Meetings",
        "path": "/vod/public-meetings"
      },
      {
        "name": "St. Johnsbury Select Board",
        "path": "/vod/stjselect"
      }
    ],
    "teaserImage": "/assets/images/vod/2024/stjselect20241209.jpg",
    "videoSource": "archive.org",
    "videoId": "katv-stjselect-mtg-120924-13583"
  },
  {
    "title": "Danville School: 2024 6-8 Winter Concert",
    "path": "/vod/concerts/2024/danville20241210",
    "nid": 2650,
    "cablecastShowId": 13585,
    "date": "2024-12-10",
    "location": "Danville",
    "year": "2024",
    "yearPath": "/vod/year/2024",
    "categories": [
      {
        "name": "Concerts",
        "path": "/vod/concerts"
      },
      {
        "name": "Danville",
        "path": "/vod/concerts/danville"
      }
    ],
    "teaserImage": "/assets/images/vod/2024/danville20241210.jpg",
    "videoSource": "vimeo",
    "videoId": "1038402155"
  },
  {
    "title": "What's Going On? Z.O.G. Escalates Wars",
    "path": "/vod/node/2651",
    "nid": 2651,
    "cablecastShowId": 13637,
    "date": "2024-12-12",
    "location": "KATV Studio",
    "year": "2024",
    "yearPath": "/vod/year/2024",
    "categories": [
      {
        "name": "Studio Programs",
        "path": "/vod/studio"
      },
      {
        "name": "What's Going On?",
        "path": "/vod/studio/wgo"
      }
    ],
    "teaserImage": "/assets/images/vod/2024/wgo20241212.jpg",
    "videoSource": "vimeo",
    "videoId": "1039340892"
  },
  {
    "title": "Lyndon Inst.: 2024 Winter Concert",
    "path": "/vod/concerts/2024/liwinter20241212",
    "nid": 2652,
    "cablecastShowId": 13590,
    "date": "2024-12-12",
    "location": "Lyndon Institute",
    "year": "2024",
    "yearPath": "/vod/year/2024",
    "categories": [
      {
        "name": "Concerts",
        "path": "/vod/concerts"
      },
      {
        "name": "Lyndon Institute",
        "path": "/vod/concerts/li"
      }
    ],
    "teaserImage": "/assets/images/vod/2024/liwinter20241212.jpg",
    "videoSource": "vimeo",
    "videoId": "1039339564"
  },
  {
    "title": "FM&P Presents: Night Owl Club - Rob Burgess",
    "path": "/vod/lectures/2024/fmp20241213",
    "nid": 2653,
    "cablecastShowId": 13620,
    "date": "2024-12-13",
    "location": "Fairbanks Museum",
    "year": "2024",
    "yearPath": "/vod/year/2024",
    "categories": [
      {
        "name": "Lectures and Forums",
        "path": "/vod/lectures-forums"
      },
      {
        "name": "Fairbanks Museum",
        "path": "/vod/fairbanks"
      }
    ],
    "teaserImage": "/assets/images/vod/2024/fmp20241213.jpg",
    "videoSource": "vimeo",
    "videoId": "1039339964"
  },
  {
    "title": "First Night North: Saint Johnsbury 2025",
    "path": "/vod/studio/2024/firstnight20241217",
    "nid": 2654,
    "cablecastShowId": 13664,
    "date": "2024-12-17",
    "location": "KATV Studio",
    "year": "2024",
    "yearPath": "/vod/year/2024",
    "categories": [
      {
        "name": "Studio Programs",
        "path": "/vod/studio"
      }
    ],
    "teaserImage": "/assets/images/vod/2024/firstnight20241217.jpg",
    "videoSource": "vimeo",
    "videoId": "1040616160"
  },
  {
    "title": "St. Johnsbury School Board: Community Budget Forum, 12/9/24",
    "path": "/vod/stjschool/2024/budget20241209",
    "nid": 2655,
    "cablecastShowId": 13633,
    "date": "2024-12-09",
    "location": "St. Johnsbury School",
    "year": "2024",
    "yearPath": "/vod/year/2024",
    "categories": [
      {
        "name": "Public Meetings",
        "path": "/vod/public-meetings"
      },
      {
        "name": "St. Johnsbury School Board",
        "path": "/vod/stjschool"
      }
    ],
    "teaserImage": "/assets/images/vod/2024/stjschoolbudget20241209.jpg",
    "videoSource": "archive.org",
    "videoId": "katv-stjschool-budget-120924-13633"
  },
  {
    "title": "St. Johnsbury School Board, 12/16/24",
    "path": "/vod/stjschool/2024/20241217",
    "nid": 2656,
    "cablecastShowId": 13626,
    "date": "2024-12-17",
    "location": "St. Johnsbury",
    "year": "2024",
    "yearPath": "/vod/year/2024",
    "categories": [
      {
        "name": "Public Meetings",
        "path": "/vod/public-meetings"
      },
      {
        "name": "St. Johnsbury School Board",
        "path": "/vod/stjschool"
      }
    ],
    "teaserImage": "/assets/images/vod/2024/stjschool20241216.jpg",
    "videoSource": "archive.org",
    "videoId": "katv-stjschool-mtg-121624-13626"
  },
  {
    "title": "STJ Academy: 2024 Winter Concert",
    "path": "/vod/concerts/2024/sja20241219",
    "nid": 2657,
    "cablecastShowId": 13589,
    "date": "2024-12-18",
    "location": "Fuller Hall, St. Johnsbury Academy",
    "year": "2024",
    "yearPath": "/vod/year/2024",
    "categories": [
      {
        "name": "Concerts",
        "path": "/vod/concerts"
      },
      {
        "name": "St. Johnsbury Academy",
        "path": "/vod/concerts/sja"
      }
    ],
    "teaserImage": "/assets/images/vod/2024/sja20241219.jpg",
    "videoSource": "vimeo",
    "videoId": "1040962309"
  },
  {
    "title": "Danville School: 2024 HS Winter Concert",
    "path": "/vod/concerts/2024/danville20241219",
    "nid": 2658,
    "cablecastShowId": 13584,
    "date": "2024-12-19",
    "location": "Danville",
    "year": "2024",
    "yearPath": "/vod/year/2024",
    "categories": [
      {
        "name": "Concerts",
        "path": "/vod/concerts"
      },
      {
        "name": "Danville",
        "path": "/vod/concerts/danville"
      }
    ],
    "teaserImage": "/assets/images/vod/2024/danville20241219.jpg",
    "videoSource": "vimeo",
    "videoId": "1040964035"
  },
  {
    "title": "Groton Select Board, 12/18/24",
    "path": "/vod/grotonselect/2024/20241218",
    "nid": 2659,
    "cablecastShowId": 13628,
    "date": "2024-12-18",
    "location": "Groton",
    "year": "2024",
    "yearPath": "/vod/year/2024",
    "categories": [
      {
        "name": "Public Meetings",
        "path": "/vod/public-meetings"
      },
      {
        "name": "Groton Select Board",
        "path": "/vod/grotonselect"
      }
    ],
    "teaserImage": "/assets/images/vod/2024/grotonselect20241218.jpg",
    "videoSource": "archive.org",
    "videoId": "katv-grotonselect-mtg-121824-13628"
  },
  {
    "title": "2025 Danville Basketball: Varsity Girls vs West Rutland",
    "path": "/vod/sports/2024/danvillegirls20241221",
    "nid": 2660,
    "cablecastShowId": 13629,
    "date": "2024-12-21",
    "location": "Danville School",
    "year": "2024",
    "yearPath": "/vod/year/2024",
    "categories": [
      {
        "name": "Local Sports",
        "path": "/vod/sports"
      }
    ],
    "teaserImage": "/assets/images/vod/2024/danvillegirls20241221.jpg",
    "videoSource": "vimeo",
    "videoId": "1041568114"
  },
  {
    "title": "2025 Danville Basketball: Varsity Boys vs Proctor",
    "path": "/vod/sports/2024/danvilleboys20241221",
    "nid": 2661,
    "cablecastShowId": 13629,
    "date": "2024-12-21",
    "location": "Danville School",
    "year": "2024",
    "yearPath": "/vod/year/2024",
    "categories": [
      {
        "name": "Local Sports",
        "path": "/vod/sports"
      }
    ],
    "teaserImage": "/assets/images/vod/2024/danvilleboys20241221.jpg",
    "videoSource": "vimeo",
    "videoId": "1041568450"
  },
  {
    "title": "St. J. Athenaeum: St. J Sparkles Holiday Celebration 2024",
    "path": "/vod/stjath/2024/20241221",
    "nid": 2662,
    "cablecastShowId": 13586,
    "date": "2024-12-21",
    "location": "St. Johnsbury Athenaeum",
    "year": "2024",
    "yearPath": "/vod/year/2024",
    "categories": [
      {
        "name": "St. Johnsbury Athenaeum",
        "path": "/vod/stjath"
      }
    ],
    "teaserImage": "/assets/images/vod/2024/stjath20241221.jpg",
    "videoSource": "vimeo",
    "videoId": "1041997741"
  },
  {
    "title": "St. Johnsbury Select Board, 12/24/24",
    "path": "/vod/stjselect/2024/20241224",
    "nid": 2663,
    "cablecastShowId": 13587,
    "date": "2024-12-24",
    "location": "St. Johnsbury Welcome Center",
    "year": "2024",
    "yearPath": "/vod/year/2024",
    "categories": [
      {
        "name": "Public Meetings",
        "path": "/vod/public-meetings"
      },
      {
        "name": "St. Johnsbury Select Board",
        "path": "/vod/stjselect"
      }
    ],
    "teaserImage": "/assets/images/vod/2024/stjselect20241223.jpg",
    "videoSource": "archive.org",
    "videoId": "katv-stjselect-mtg-122324-13587"
  },
  {
    "title": "What's Going On? Round & Round We Go",
    "path": "/vod/wgo/wgo20241227",
    "nid": 2664,
    "cablecastShowId": 13685,
    "date": "2024-12-27",
    "location": "KATV Studio",
    "year": "2024",
    "yearPath": "/vod/year/2024",
    "categories": [
      {
        "name": "Studio Programs",
        "path": "/vod/studio"
      },
      {
        "name": "What's Going On?",
        "path": "/vod/studio/wgo"
      }
    ],
    "teaserImage": "/assets/images/vod/2024/wgo20241227.jpg",
    "videoSource": "vimeo",
    "videoId": "1042639310"
  },
  {
    "title": "2025 Danville Basketball: JV Boys vs WRV",
    "path": "/vod/sports/2024/danvillejvboys20241227",
    "nid": 2665,
    "cablecastShowId": 13667,
    "date": "2024-12-27",
    "location": "Danville",
    "year": "2024",
    "yearPath": "/vod/year/2024",
    "categories": [
      {
        "name": "Local Sports",
        "path": "/vod/sports"
      }
    ],
    "teaserImage": "/assets/images/vod/2024/danvillejvboys20241227.jpg",
    "videoSource": "vimeo",
    "videoId": "1042789826"
  },
  {
    "title": "2025 Danville Basketball: Varsity Boys vs WRV",
    "path": "/vod/sports/2024/danvillevboys20241227",
    "nid": 2666,
    "cablecastShowId": 13668,
    "date": "2024-12-27",
    "location": "Danville",
    "year": "2024",
    "yearPath": "/vod/year/2024",
    "categories": [
      {
        "name": "Local Sports",
        "path": "/vod/sports"
      }
    ],
    "teaserImage": "/assets/images/vod/2024/danvillevboys20241227.jpg",
    "videoSource": "vimeo",
    "videoId": "1042790025"
  }
]